{
	"cmake" : 
	{
		"generator" : 
		{
			"multiConfig" : false,
			"name" : "Ninja"
		},
		"paths" : 
		{
			"cmake" : "/home/mathias/.local/share/JetBrains/Toolbox/apps/CLion/ch-0/222.4167.35/bin/cmake/linux/bin/cmake",
			"cpack" : "/home/mathias/.local/share/JetBrains/Toolbox/apps/CLion/ch-0/222.4167.35/bin/cmake/linux/bin/cpack",
			"ctest" : "/home/mathias/.local/share/JetBrains/Toolbox/apps/CLion/ch-0/222.4167.35/bin/cmake/linux/bin/ctest",
			"root" : "/home/mathias/.local/share/JetBrains/Toolbox/apps/CLion/ch-0/222.4167.35/bin/cmake/linux/share/cmake-3.23"
		},
		"version" : 
		{
			"isDirty" : false,
			"major" : 3,
			"minor" : 23,
			"patch" : 2,
			"string" : "3.23.2",
			"suffix" : ""
		}
	},
	"objects" : 
	[
		{
			"jsonFile" : "codemodel-v2-1c3de6c39e8e7e17f183.json",
			"kind" : "codemodel",
			"version" : 
			{
				"major" : 2,
				"minor" : 4
			}
		},
		{
			"jsonFile" : "cache-v2-d3703e5a061c579e6cea.json",
			"kind" : "cache",
			"version" : 
			{
				"major" : 2,
				"minor" : 0
			}
		},
		{
			"jsonFile" : "cmakeFiles-v1-e6664d43dd7178d39a47.json",
			"kind" : "cmakeFiles",
			"version" : 
			{
				"major" : 1,
				"minor" : 0
			}
		},
		{
			"jsonFile" : "toolchains-v1-e08abe09ec0b17341edb.json",
			"kind" : "toolchains",
			"version" : 
			{
				"major" : 1,
				"minor" : 0
			}
		}
	],
	"reply" : 
	{
		"cache-v2" : 
		{
			"jsonFile" : "cache-v2-d3703e5a061c579e6cea.json",
			"kind" : "cache",
			"version" : 
			{
				"major" : 2,
				"minor" : 0
			}
		},
		"cmakeFiles-v1" : 
		{
			"jsonFile" : "cmakeFiles-v1-e6664d43dd7178d39a47.json",
			"kind" : "cmakeFiles",
			"version" : 
			{
				"major" : 1,
				"minor" : 0
			}
		},
		"codemodel-v2" : 
		{
			"jsonFile" : "codemodel-v2-1c3de6c39e8e7e17f183.json",
			"kind" : "codemodel",
			"version" : 
			{
				"major" : 2,
				"minor" : 4
			}
		},
		"toolchains-v1" : 
		{
			"jsonFile" : "toolchains-v1-e08abe09ec0b17341edb.json",
			"kind" : "toolchains",
			"version" : 
			{
				"major" : 1,
				"minor" : 0
			}
		}
	}
}
